[
{
    "Country": "Afghanistan",
    "LEAB_MValue": 44.87705454545455,
    "LEAB_FValue": 46.715163636363634
},
{
    "Country": "Armenia",
    "LEAB_MValue": 65.89718181818182,
    "LEAB_FValue": 72.17401818181818
},
{
    "Country": "Azerbaijan",
    "LEAB_MValue": 61.05283636363639,
    "LEAB_FValue": 68.05807272727273
},
{
    "Country": "Bahrain",
    "LEAB_MValue": 66.74876363636363,
    "LEAB_FValue": 69.71621818181816
},
{
    "Country": "Bangladesh",
    "LEAB_MValue": 55.984563636363625,
    "LEAB_FValue": 56.74981818181819
},
{
    "Country": "Bhutan",
    "LEAB_MValue": 49.1966909090909,
    "LEAB_FValue": 49.25647272727272
},
{
    "Country": "Brunei Darussalam",
    "LEAB_MValue": 68.76567272727273,
    "LEAB_FValue": 71.79107272727275
},
{
    "Country": "Cambodia",
    "LEAB_MValue": 45.116472727272736,
    "LEAB_FValue": 49.62223636363636
},
{
    "Country": "China",
    "LEAB_MValue": 63.865963636363645,
    "LEAB_FValue": 66.61785454545453
},
{
    "Country": "Cyprus",
    "LEAB_MValue": 72.1556,
    "LEAB_FValue": 76.21452727272725
},
{
    "Country": "Georgia",
    "LEAB_MValue": 64.74785454545454,
    "LEAB_FValue": 72.15105454545454
},
{
    "Country": "India",
    "LEAB_MValue": 54.63734545454547,
    "LEAB_FValue": 55.09919999999999
},
{
    "Country": "Indonesia",
    "LEAB_MValue": 58.365836363636376,
    "LEAB_FValue": 61.27227272727273
},
{
    "Country": "Iraq",
    "LEAB_MValue": 60.370163636363635,
    "LEAB_FValue": 64.65876363636366
},
{
    "Country": "Israel",
    "LEAB_MValue": 67.58054545454543,
    "LEAB_FValue": 70.77527272727274
},
{
    "Country": "Japan",
    "LEAB_MValue": 73.07309090909092,
    "LEAB_FValue": 78.7010909090909
},
{
    "Country": "Jordan",
    "LEAB_MValue": 64.26723636363634,
    "LEAB_FValue": 66.75019999999999
},
{
    "Country": "Kazakhstan",
    "LEAB_MValue": 58.99530909090909,
    "LEAB_FValue": 69.10938181818182
},
{
    "Country": "Kuwait",
    "LEAB_MValue": 67.6974,
    "LEAB_FValue": 69.91581818181815
},
{
    "Country": "Lebanon",
    "LEAB_MValue": 67.58167272727273,
    "LEAB_FValue": 71.05274545454544
},
{
    "Country": "Malaysia",
    "LEAB_MValue": 66.11750909090908,
    "LEAB_FValue": 69.36641818181818
},
{
    "Country": "Maldives",
    "LEAB_MValue": 57.14869090909092,
    "LEAB_FValue": 57.19414545454546
},
{
    "Country": "Mongolia",
    "LEAB_MValue": 55.59301818181817,
    "LEAB_FValue": 60.96136363636364
},
{
    "Country": "Myanmar",
    "LEAB_MValue": 53.348745454545444,
    "LEAB_FValue": 57.923254545454554
},
{
    "Country": "Nepal",
    "LEAB_MValue": 50.42774545454545,
    "LEAB_FValue": 51.71709090909092
},
{
    "Country": "Oman",
    "LEAB_MValue": 59.9024,
    "LEAB_FValue": 63.21240000000003
},
{
    "Country": "Pakistan",
    "LEAB_MValue": 56.542618181818185,
    "LEAB_FValue": 57.58767272727274
},
{
    "Country": "Philippines",
    "LEAB_MValue": 60.28730909090909,
    "LEAB_FValue": 65.1382909090909
},
{
    "Country": "Qatar",
    "LEAB_MValue": 70.29714545454547,
    "LEAB_FValue": 72.77538181818184
},
{
    "Country": "Saudi Arabia",
    "LEAB_MValue": 61.17819999999998,
    "LEAB_FValue": 64.59885454545453
},
{
    "Country": "Singapore",
    "LEAB_MValue": 70.0552,
    "LEAB_FValue": 75.25856363636363
},
{
    "Country": "Sri Lanka",
    "LEAB_MValue": 64.4385818181818,
    "LEAB_FValue": 69.95254545454546
},
{
    "Country": "Syrian Arab Republic",
    "LEAB_MValue": 64.66667272727273,
    "LEAB_FValue": 66.95338181818182
},
{
    "Country": "Tajikistan",
    "LEAB_MValue": 58.651618181818186,
    "LEAB_FValue": 64.47563636363634
},
{
    "Country": "Thailand",
    "LEAB_MValue": 62.13874545454547,
    "LEAB_FValue": 68.13707272727274
},
{
    "Country": "Timor-Leste",
    "LEAB_MValue": 45.620927272727265,
    "LEAB_FValue": 47.8068
},
{
    "Country": "Turkey",
    "LEAB_MValue": 57.4900909090909,
    "LEAB_FValue": 64.04996363636363
},
{
    "Country": "Turkmenistan",
    "LEAB_MValue": 56.63716363636365,
    "LEAB_FValue": 64.01930909090909
},
{
    "Country": "United Arab Emirates",
    "LEAB_MValue": 65.93152727272728,
    "LEAB_FValue": 68.97085454545454
},
{
    "Country": "Uzbekistan",
    "LEAB_MValue": 60.783236363636355,
    "LEAB_FValue": 67.39434545454547
},
{
    "Country": "Vietnam",
    "LEAB_MValue": 62.57174545454545,
    "LEAB_FValue": 71.5874
}]